{
  "images" : [
    {
      "src": "http://res.cloudinary.com/mxmrcl/image/upload/f_auto,w_1100,c_scale,q_80/octopus_rgwflh.jpg",
      "title": "EIGHT",
      "id": 1
    },
    {
      "src": "http://res.cloudinary.com/mxmrcl/image/upload/f_auto,w_1100,c_scale,q_80/stroll_drn0qo.jpg",
      "title": "STROLL",
      "id": 2
    },
    {
      "src": "http://res.cloudinary.com/mxmrcl/image/upload/f_auto,w_1100,c_scale,q_80/lay_hzyzdj.jpg",
      "title": "LAY",
      "id": 3
    },
    {
      "src": "http://res.cloudinary.com/mxmrcl/image/upload/f_auto,w_1100,c_scale,q_80/chop_mfafbg.jpg",
      "title": "CHOP",
      "id": 4
    },
    {
      "src": "http://res.cloudinary.com/mxmrcl/image/upload/f_auto,w_1100,c_scale,q_80/bask_dxygt7.jpg",
      "title": "BASK",
      "id": 5
    },
    {
      "src": "http://res.cloudinary.com/mxmrcl/image/upload/f_auto,w_1100,c_scale,q_80/drank_qowyip.jpg",
      "title": "DRANK",
      "id": 6
    },
    {
      "src": "http://res.cloudinary.com/mxmrcl/image/upload/f_auto,w_1100,c_scale,q_80/FOLLOW_ecdjnd.jpg",
      "title": "FOLLOW",
      "id": 7
    },
    {
      "src": "http://res.cloudinary.com/mxmrcl/image/upload/f_auto,w_1100,c_scale,q_80/EYE_mszc7n.jpg",
      "title": "EYE",
      "id": 8
    },
    {
      "src": "http://res.cloudinary.com/mxmrcl/image/upload/f_auto,w_1100,c_scale,q_80/EMPIRE_ueiudq.jpg",
      "title": "EMPIRE",
      "id": 9
    },
    {
      "src": "http://res.cloudinary.com/mxmrcl/image/upload/f_auto,w_1100,c_scale,q_80/BREATHE_qatq86.jpg",
      "title": "BREATHE",
      "id": 10
    },
    {
      "src": "http://res.cloudinary.com/mxmrcl/image/upload/f_auto,w_1100,c_scale,q_80/WAGE_qiiodq.jpg",
      "title": "SLAVE TO THE WAGE",
      "id": 11
    }
  ]
}